my_package/__init__.py
my_package/main.py
mcm_python-0.1.dist-info/LICENSE
mcm_python-0.1.dist-info/METADATA
mcm_python-0.1.dist-info/WHEEL
mcm_python-0.1.dist-info/top_level.txt
mcm_python-0.1.dist-info/RECORD
