Metadata-Version: 2.1
Name: mcm-python
Version: 0.1
Summary: A simple Python package for My Country Mobile
Home-page: https://github.com/Mycountrymobile-com/mcm-python/
Author: Ariyan
Author-email: ariyan@mycountrymobile.com
Classifier: Programming Language :: Python :: 3
Classifier: License :: OSI Approved :: MIT License
Classifier: Operating System :: OS Independent
License-File: LICENSE
